kremographer/__init__.py
kremographer/cli.py
kremographer-1.0.0.dist-info/licenses/LICENSE
kremographer-1.0.0.dist-info/METADATA
kremographer-1.0.0.dist-info/WHEEL
kremographer-1.0.0.dist-info/entry_points.txt
kremographer-1.0.0.dist-info/top_level.txt
kremographer-1.0.0.dist-info/RECORD
