Metadata-Version: 2.4
Name: kremographer
Version: 1.0.0
Summary: AES-GCM file encryption/decryption CLI tool
Author-email: Kareem Mahfouf <kareem.mahfouf@gmail.com>
License: MIT License
Requires-Python: >=3.8
License-File: LICENSE
Requires-Dist: cryptography>=42.0
Dynamic: license-file
